v2_samplesheet_maker/__init__.py
v2_samplesheet_maker/enums.py
v2_samplesheet_maker/globals.py
v2_samplesheet_maker/classes/__init__.py
v2_samplesheet_maker/classes/samplesheet.py
v2_samplesheet_maker/classes/super_sections.py
v2_samplesheet_maker/functions/__init__.py
v2_samplesheet_maker/functions/run_info_reader.py
v2_samplesheet_maker/functions/run_info_writer.py
v2_samplesheet_maker/functions/v2_samplesheet_reader.py
v2_samplesheet_maker/functions/v2_samplesheet_to_run_info.py
v2_samplesheet_maker/functions/v2_samplesheet_writer.py
v2_samplesheet_maker/models/__init__.py
v2_samplesheet_maker/models/bcl_convert_sections.py
v2_samplesheet_maker/models/cloud_section.py
v2_samplesheet_maker/models/run_info_sections.py
v2_samplesheet_maker/models/samplesheet.py
v2_samplesheet_maker/models/tso500l_sections.py
v2_samplesheet_maker/models/tso500s_sections.py
v2_samplesheet_maker/run/__init__.py
v2_samplesheet_maker/run/run_info_reader.py
v2_samplesheet_maker/run/run_info_writer.py
v2_samplesheet_maker/run/v2_samplesheet_reader.py
v2_samplesheet_maker/run/v2_samplesheet_to_run_info_xml.py
v2_samplesheet_maker/run/v2_samplesheet_writer.py
v2_samplesheet_maker/section_classes/bcl_convert_sections.py
v2_samplesheet_maker/section_classes/cloud_sections.py
v2_samplesheet_maker/section_classes/run_info_sections.py
v2_samplesheet_maker/section_classes/tso500l_sections.py
v2_samplesheet_maker/section_classes/tso500s_sections.py
v2_samplesheet_maker/utils/__init__.py
v2_samplesheet_maker/utils/cli.py
v2_samplesheet_maker/utils/docopt_docs.py
v2_samplesheet_maker/utils/logger.py
v2_samplesheet_maker/utils/xml.py
v2_samplesheet_maker-4.2.4.post20241110133537.data/scripts/build-samplesheet-and-validate-with-bcl-convert.sh
v2_samplesheet_maker-4.2.4.post20241110133537.dist-info/LICENSE
v2_samplesheet_maker-4.2.4.post20241110133537.dist-info/METADATA
v2_samplesheet_maker-4.2.4.post20241110133537.dist-info/WHEEL
v2_samplesheet_maker-4.2.4.post20241110133537.dist-info/entry_points.txt
v2_samplesheet_maker-4.2.4.post20241110133537.dist-info/top_level.txt
v2_samplesheet_maker-4.2.4.post20241110133537.dist-info/RECORD
